eevalue/__init__.py
eevalue/__main__.py
eevalue/exceptions.py
eevalue/logging.py
eevalue/pyproject.toml
eevalue/settings.py
eevalue/utils.py
eevalue/build_data/__init__.py
eevalue/build_data/forward.py
eevalue/build_data/historical.py
eevalue/calibrate/__init__.py
eevalue/calibrate/inputs.py
eevalue/cli/__init__.py
eevalue/cli/backtest.py
eevalue/cli/calibrate.py
eevalue/cli/common.py
eevalue/cli/compare.py
eevalue/cli/ordc.py
eevalue/cli/preprocess.py
eevalue/cli/replay.py
eevalue/cli/runs.py
eevalue/cli/simulate.py
eevalue/config/EL/config.yml
eevalue/config/EL/scenarios/capacity.csv
eevalue/config/EL/scenarios/carbon.csv
eevalue/config/EL/scenarios/demand.csv
eevalue/config/EL/scenarios/gas.csv
eevalue/config/EL/scenarios/lignite.csv
eevalue/config/EL/scenarios/solar.csv
eevalue/config/EL/scenarios/storage.csv
eevalue/config/EL/scenarios/wind.csv
eevalue/preprocess/__init__.py
eevalue/preprocess/clusters.py
eevalue/simulate/__init__.py
eevalue/simulate/inputs.py
eevalue/simulate/model.py
eevalue/simulate/postprocess.py
eevalue_tool-0.1.dist-info/LICENSE
eevalue_tool-0.1.dist-info/METADATA
eevalue_tool-0.1.dist-info/WHEEL
eevalue_tool-0.1.dist-info/entry_points.txt
eevalue_tool-0.1.dist-info/top_level.txt
eevalue_tool-0.1.dist-info/RECORD
