Metadata-Version: 2.1
Name: eevalue-tool
Version: 0.1
Summary: A library for estimating the value of energy efficiency as a grid resource
Home-page: https://github.com/hebes-io/eevalue
Keywords: power market,power system,simulation,calibration
Classifier: Development Status :: 4 - Beta
Classifier: Intended Audience :: Science/Research
Classifier: Intended Audience :: Developers
Classifier: License :: OSI Approved :: MIT License
Classifier: Programming Language :: Python :: 3
Classifier: Programming Language :: Python :: 3.7
Classifier: Programming Language :: Python :: 3.8
Classifier: Programming Language :: Python :: 3.9
Classifier: Programming Language :: Python :: 3.10
Classifier: Topic :: Scientific/Engineering
Classifier: Operating System :: OS Independent
Requires-Python: >=3.7
License-File: LICENSE
Requires-Dist: blosc (>=1.11.1)
Requires-Dist: colorlog (>=6.7.0)
Requires-Dist: mlflow (>=2.2.2)
Requires-Dist: omegaconf (>=2.3.0)
Requires-Dist: power-markets (>=0.1)
Requires-Dist: pydantic (>=1.10.7)
Requires-Dist: pyomo (>=6.5.0)
Requires-Dist: rich (>=13.3.3)
Requires-Dist: scikit-learn (>=1.2.2)
